CHANGES.txt
LICENSE.txt
MANIFEST.in
README.txt
setup.py
PyLogWatch.egg-info/PKG-INFO
PyLogWatch.egg-info/SOURCES.txt
PyLogWatch.egg-info/dependency_links.txt
PyLogWatch.egg-info/requires.txt
PyLogWatch.egg-info/top_level.txt
bin/pylog.py
pylogwatch/__init__.py
pylogwatch/logwlib.py
pylogwatch/utils.py
pylogwatch/formatters/__init__.py
pylogwatch/formatters/base.py
pylogwatch/formatters/git.py
pylogwatch/formatters/web.py