Metadata-Version: 1.0
Name: PyLogWatch
Version: 0.1.9-alpha2
Summary: Python utility to parse log files and send them to a Sentry server.
Home-page: http://pypi.python.org/pypi/PyLogWatch/
Author: E. Filipov, MTR Design
Author-email: pylogwatch@mtr-design.com
License: LICENSE.txt
Platform: UNKNOWN
